fmi_bd2cmake/__init__.py
fmi_bd2cmake/cli.py
fmi_bd2cmake/generator.py
fmi_bd2cmake/parser.py
fmi_bd2cmake-0.1.0.dist-info/licenses/LICENSE
fmi_bd2cmake-0.1.0.dist-info/METADATA
fmi_bd2cmake-0.1.0.dist-info/WHEEL
fmi_bd2cmake-0.1.0.dist-info/entry_points.txt
fmi_bd2cmake-0.1.0.dist-info/top_level.txt
fmi_bd2cmake-0.1.0.dist-info/RECORD
